django_email_validators/__init__.py
django_email_validators/apps.py
django_email_validators/metadata.py
django_email_validators/providers.py
django_email_validators/utils.py
django_email_validators/validators.py
django_email_validators/locale/de/LC_MESSAGES/django.po
django_email_validators/locale/en/LC_MESSAGES/django.po
django_email_validators/locale/es/LC_MESSAGES/django.po
django_email_validators/locale/fr/LC_MESSAGES/django.po
django_email_validators/locale/it/LC_MESSAGES/django.po
django_email_validators/locale/uk/LC_MESSAGES/django.po
django_email_validators-0.2.1.dist-info/licenses/LICENSE.txt
django_email_validators-0.2.1.dist-info/METADATA
django_email_validators-0.2.1.dist-info/WHEEL
django_email_validators-0.2.1.dist-info/top_level.txt
django_email_validators-0.2.1.dist-info/RECORD
