Metadata-Version: 2.4
Name: django-email-validators
Version: 0.2.1
Summary: no more invalid or disposable emails in your database.
Author-email: Fabio Caccamo <fabio.caccamo@gmail.com>
Maintainer-email: Fabio Caccamo <fabio.caccamo@gmail.com>
License: MIT License
Project-URL: Homepage, https://github.com/fabiocaccamo/django-email-validators
Project-URL: Download, https://github.com/fabiocaccamo/django-email-validators/releases
Project-URL: Documentation, https://github.com/fabiocaccamo/django-email-validators#readme
Project-URL: Issues, https://github.com/fabiocaccamo/django-email-validators/issues
Project-URL: Funding, https://github.com/sponsors/fabiocaccamo/
Project-URL: Twitter, https://twitter.com/fabiocaccamo
Keywords: python,django,email,validation,validator,disposable,deliverable,mx,check,strict,validator,verification
Classifier: Development Status :: 5 - Production/Stable
Classifier: Environment :: Web Environment
Classifier: Framework :: Django
Classifier: Framework :: Django :: 4.0
Classifier: Framework :: Django :: 4.1
Classifier: Framework :: Django :: 4.2
Classifier: Framework :: Django :: 5.0
Classifier: Framework :: Django :: 5.1
Classifier: Framework :: Django :: 5.2
Classifier: Framework :: Django :: 6.0
Classifier: Intended Audience :: Developers
Classifier: License :: OSI Approved :: MIT License
Classifier: Natural Language :: English
Classifier: Operating System :: OS Independent
Classifier: Programming Language :: Python :: 3
Classifier: Programming Language :: Python :: 3.10
Classifier: Programming Language :: Python :: 3.11
Classifier: Programming Language :: Python :: 3.12
Classifier: Programming Language :: Python :: 3.13
Classifier: Programming Language :: Python :: 3.14
Classifier: Topic :: Communications :: Email
Classifier: Topic :: Internet :: WWW/HTTP
Classifier: Topic :: Software Development :: Libraries :: Python Modules
License-File: LICENSE.txt
Requires-Dist: disposable-email-domains<1.0.0,>=0.0.147
Requires-Dist: email-validator<3.0.0,>=2.3.0
Requires-Dist: mailchecker<7.0.0,>=6.0.19
Requires-Dist: pyIsEmail<3.0.0,>=2.0.1
Dynamic: license-file
